js2py/__init__.py
js2py/base.py
js2py/evaljs.py
js2py/node_import.py
js2py/pyjs.py
js2py/constructors/__init__.py
js2py/constructors/jsarray.py
js2py/constructors/jsarraybuffer.py
js2py/constructors/jsboolean.py
js2py/constructors/jsdate.py
js2py/constructors/jsfloat32array.py
js2py/constructors/jsfloat64array.py
js2py/constructors/jsfunction.py
js2py/constructors/jsint16array.py
js2py/constructors/jsint32array.py
js2py/constructors/jsint8array.py
js2py/constructors/jsmath.py
js2py/constructors/jsnumber.py
js2py/constructors/jsobject.py
js2py/constructors/jsregexp.py
js2py/constructors/jsstring.py
js2py/constructors/jsuint16array.py
js2py/constructors/jsuint32array.py
js2py/constructors/jsuint8array.py
js2py/constructors/jsuint8clampedarray.py
js2py/constructors/time_helpers.py
js2py/es6/__init__.py
js2py/es6/babel.py
js2py/host/__init__.py
js2py/host/console.py
js2py/host/jseval.py
js2py/host/jsfunctions.py
js2py/internals/__init__.py
js2py/internals/base.py
js2py/internals/byte_trans.py
js2py/internals/code.py
js2py/internals/conversions.py
js2py/internals/desc.py
js2py/internals/fill_space.py
js2py/internals/func_utils.py
js2py/internals/gen.py
js2py/internals/opcodes.py
js2py/internals/operations.py
js2py/internals/seval.py
js2py/internals/simplex.py
js2py/internals/space.py
js2py/internals/speed.py
js2py/internals/trans_utils.py
js2py/internals/constructors/__init__.py
js2py/internals/constructors/jsarray.py
js2py/internals/constructors/jsboolean.py
js2py/internals/constructors/jsconsole.py
js2py/internals/constructors/jsdate.py
js2py/internals/constructors/jsfunction.py
js2py/internals/constructors/jsmath.py
js2py/internals/constructors/jsnumber.py
js2py/internals/constructors/jsobject.py
js2py/internals/constructors/jsregexp.py
js2py/internals/constructors/jsstring.py
js2py/internals/constructors/time_helpers.py
js2py/internals/prototypes/__init__.py
js2py/internals/prototypes/jsarray.py
js2py/internals/prototypes/jsboolean.py
Js2Py2-0.75.dist-info/LICENSE.md
Js2Py2-0.75.dist-info/METADATA
Js2Py2-0.75.dist-info/WHEEL
Js2Py2-0.75.dist-info/top_level.txt
Js2Py2-0.75.dist-info/RECORD
