Metadata-Version: 2.2
Name: Js2Py2
Version: 0.75
Summary: JavaScript to Python Translator & JavaScript interpreter written in 100% pure Python.
Home-page: https://github.com/PiotrDabkowski/Js2Py
Author: Timur Kutsenko
Author-email: kutsenko.timur@gmail.com
License: MIT
License-File: LICENSE.md
Requires-Dist: tzlocal>=1.2
Requires-Dist: six>=1.10
Requires-Dist: pyjsparser>=2.5.1
Dynamic: author
Dynamic: author-email
Dynamic: description
Dynamic: home-page
Dynamic: license
Dynamic: requires-dist
Dynamic: summary
